maeluma/__init__.py
maeluma/client.py
maeluma/client_async.py
maeluma/custom_model_dataset.py
maeluma/embeddings.py
maeluma/enums.py
maeluma/error.py
maeluma/logging.py
maeluma/responses/__init__.py
maeluma/responses/base.py
maeluma/responses/chat.py
maeluma/responses/embeddings.py
maeluma/responses/image.py
maeluma/responses/image_generation.py
maeluma/responses/summarize.py
maeluma/responses/text_generation.py
maeluma/responses/tokenize.py
maeluma/responses/upscale.py
maeluma/utils.py
maeluma-0.0.1.dist-info/LICENSE
maeluma-0.0.1.dist-info/METADATA
maeluma-0.0.1.dist-info/WHEEL
maeluma-0.0.1.dist-info/RECORD
