Metadata-Version: 2.1
Name: maeluma
Version: 0.0.1
Summary: 
Author: Maeluma
Requires-Python: >=3.7,<4.0
Classifier: Programming Language :: Python :: 3
Classifier: Programming Language :: Python :: 3.7
Classifier: Programming Language :: Python :: 3.8
Classifier: Programming Language :: Python :: 3.9
Classifier: Programming Language :: Python :: 3.10
Classifier: Programming Language :: Python :: 3.11
Requires-Dist: aiohttp (>=3.0,<4.0)
Requires-Dist: backoff (>=2.0,<3.0)
Requires-Dist: importlib_metadata (>=6.0,<7.0)
Requires-Dist: requests (>=2.0,<3.0)
Requires-Dist: urllib3 (>=2.0.3,<3.0.0)
